libarvo/__init__.py
libarvo/arvo.py
libarvo/lib.py
libarvo/libarvo.dll
libarvo/libarvo.dll.a
libarvo/mytyping.py
libarvo-0.1.2.dist-info/LICENSE
libarvo-0.1.2.dist-info/LICENSE_bundled.txt
libarvo-0.1.2.dist-info/METADATA
libarvo-0.1.2.dist-info/WHEEL
libarvo-0.1.2.dist-info/top_level.txt
libarvo-0.1.2.dist-info/RECORD
