Metadata-Version: 2.1
Name: libarvo
Version: 0.1.2
Summary: Python library for arvo
Home-page: https://github.com/rlaplaza/libarvo
Author: R. Laplaza
Author-email: rlaplaza@duck.com
License: MIT
Classifier: Programming Language :: Python :: 3
Classifier: License :: OSI Approved :: MIT License
Classifier: Operating System :: OS Independent
Requires-Python: >=3.8
License-File: LICENSE
License-File: LICENSE_bundled.txt
